autoPVM/PVM.py
autoPVM/__init__.py
autoPVM-0.3.dist-info/LICENSE
autoPVM-0.3.dist-info/METADATA
autoPVM-0.3.dist-info/WHEEL
autoPVM-0.3.dist-info/top_level.txt
autoPVM-0.3.dist-info/RECORD
