Metadata-Version: 2.1
Name: autoPVM
Version: 0.3
Summary: Automatically conducting a PVM Analysis
Home-page: UNKNOWN
Author: Akash Sonthalia
Author-email: <axsonthalia@gmail.com>
License: UNKNOWN
Keywords: python,data,analysis,data analysis,business analysis,PVM Analysis
Platform: UNKNOWN
Classifier: Intended Audience :: Developers
Classifier: Programming Language :: Python :: 3
Classifier: Operating System :: Unix
Classifier: Operating System :: MacOS :: MacOS X
Classifier: Operating System :: Microsoft :: Windows
Requires-Dist: numpy
Requires-Dist: pandas
Requires-Dist: plotly
